examples/__init__.py
examples/custom_llm_openai_example.py
examples/export_import_example.py
examples/groq_chat_example.py
examples/semantic_search_example.py
statecall/__init__.py
statecall/groq_client.py
statecall/memory.py
statecall/semantic_search.py
statecall-0.2.1.dist-info/licenses/LICENSE
statecall-0.2.1.dist-info/METADATA
statecall-0.2.1.dist-info/WHEEL
statecall-0.2.1.dist-info/top_level.txt
statecall-0.2.1.dist-info/RECORD
